{
  "_fv": 69,
  "_type": "tool",
  "definition": {
    "toolType": "Special",
    "renderType": 0,
    "blockingRenderType": 0,
    "texture": "herbs_whip",
    "customModelName": "Normal",
    "blockingModelName": "Normal blocking",
    "name": "Herbs Whip",
    "specialInformation": {
      "fixedValue": []
    },
    "creativeTabs": [
      {
        "value": "TOOLS"
      }
    ],
    "efficiency": 4.0,
    "attackSpeed": 1.2,
    "enchantability": 2,
    "damageVsEntity": 1.0,
    "usageCount": 30,
    "glowCondition": {
      "fixedValue": false
    },
    "repairItems": [],
    "immuneToFire": false,
    "blockDropsTier": "WOOD",
    "blocksAffected": [
      {
        "value": "Blocks.DOUBLE_PLANT#2"
      },
      {
        "value": "Blocks.DOUBLE_PLANT#3"
      },
      {
        "value": "Blocks.TALLGRASS#1"
      },
      {
        "value": "Blocks.TALLGRASS#2"
      },
      {
        "value": "Blocks.TALLGRASS"
      }
    ],
    "stayInGridWhenCrafting": false,
    "damageOnCrafting": false,
    "onBlockDestroyedWithTool": {
      "name": "HerbsWhipBlockDestroyedWithTool"
    }
  }
}